PEViT/__init__.py
PEViT/tools/__init__.py
PEViT/tools/_init_paths.py
PEViT/tools/bit_finetune.py
PEViT/tools/eval.py
PEViT/tools/eval_direct.py
PEViT/tools/eval_intrinsic_dimension.py
PEViT/tools/eval_local.py
PEViT/tools/eval_metric.py
PEViT/tools/finetune.py
PEViT/tools/finetune_1st_attention.py
PEViT/tools/finetune_1st_mlp.py
PEViT/tools/finetune_adapter.py
PEViT/tools/finetune_attention.py
PEViT/tools/finetune_attention_position_bias.py
PEViT/tools/finetune_bias.py
PEViT/tools/finetune_cswin.py
PEViT/tools/finetune_kadapter.py
PEViT/tools/finetune_layernorm.py
PEViT/tools/finetune_lora.py
PEViT/tools/finetune_lora_adapter.py
PEViT/tools/finetune_lora_drop_adapter.py
PEViT/tools/finetune_lora_fix_one.py
PEViT/tools/finetune_lr_group.py
PEViT/tools/intrinsic_dimension.py
PEViT/tools/linear_probe.py
PEViT/tools/model_summary.py
PEViT/tools/swa_finetune.py
PEViT/tools/test.py
PEViT/tools/test_clip_retrieval.py
PEViT/tools/test_clip_zeroshot.py
PEViT/tools/test_io.py
PEViT/tools/train.py
PEViT/tools/train_clip.py
PEViT-0.0.8.dist-info/METADATA
PEViT-0.0.8.dist-info/WHEEL
PEViT-0.0.8.dist-info/top_level.txt
PEViT-0.0.8.dist-info/RECORD
