Metadata-Version: 2.1
Name: PEViT
Version: 0.0.8
Summary: Parameter-efficient Finetuning for ViT
Home-page: https://github.com/jkooy/KroneckerAdapter
Author: xuehaihe
Author-email: xuehaihe2008@gmail.com
License: UNKNOWN
Platform: UNKNOWN
Requires-Python: >=3.6
